peepshow/__init__.py
peepshow/cmds/__init__.py
peepshow/cmds/base.py
peepshow/cmds/cmds.py
peepshow/core/__init__.py
peepshow/core/context.py
peepshow/core/dialect.py
peepshow/core/env.py
peepshow/core/exceptions.py
peepshow/core/explorer.py
peepshow/core/goto.py
peepshow/core/peep.py
peepshow/core/probes.py
peepshow/core/show.py
peepshow/core/trans.py
peepshow/pager/__init__.py
peepshow/pager/cache.py
peepshow/pager/pager.py
peepshow/peep.py
peepshow/peepshow.1
peepshow/show.py
peepshow/utils/__init__.py
peepshow/utils/magic_peep.py
peepshow/utils/python.py
peepshow/utils/system.py
peepshow/utils/terminal.py
peepshow/utils/traceback.py
peepshow-0.3.0.dist-info/LICENSE
peepshow-0.3.0.dist-info/METADATA
peepshow-0.3.0.dist-info/WHEEL
peepshow-0.3.0.dist-info/RECORD
