Metadata-Version: 2.1
Name: peepshow
Version: 0.3.0
Summary: Python data explorer.
Home-page: https://gergelyk.github.io/peepshow
License: MIT
Keywords: debug,data,explore,programming
Author: Grzegorz Krasoń
Author-email: grzegorz.krason@gmail.com
Requires-Python: >=3.6,<4.0
Classifier: License :: OSI Approved :: MIT License
Classifier: Programming Language :: Python :: 3
Classifier: Programming Language :: Python :: 3.6
Classifier: Programming Language :: Python :: 3.7
Classifier: Programming Language :: Python :: 3.8
Classifier: Programming Language :: Python :: 3.9
Classifier: Programming Language :: Python :: 3.10
Classifier: Programming Language :: Python :: 3.11
Requires-Dist: astor (>=0.8.1,<0.9.0)
Requires-Dist: astunparse (>=1.6.3,<2.0.0)
Requires-Dist: colorama (>=0.4.4,<0.5.0)
Requires-Dist: miscutils (>=1.4.0,<2.0.0)
Requires-Dist: pprintpp (>=0.4.0,<0.5.0)
Requires-Dist: py-getch (>=1.0.1,<2.0.0)
Requires-Dist: pygments (>=2.7.2,<3.0.0)
Project-URL: Documentation, https://gergelyk.github.io/peepshow
Project-URL: Repository, https://github.com/gergelyk/peepshow
